{"type":"FeatureCollection","features":[{"geometry":{"coordinates":[-94.0574061,33.1379088],"type":"Point"},"properties":{"Age":"","AgeGroup":"3","City":"Bloomburg","NumberofDeaths":1,"NumberofFemale":1,"NumberofMale":0,"State":"TX"},"type":"Feature"}]}