{"type":"FeatureCollection","features":[{"geometry":{"coordinates":[-96.4836221,35.4934062],"type":"Point"},"properties":{"Age":53,"AgeGroup":"3","City":"Boley","NumberofDeaths":2,"NumberofFemale":1,"NumberofMale":1,"State":"OK"},"type":"Feature"}]}