{"type":"FeatureCollection","features":[{"geometry":{"coordinates":[-94.2008288,46.3580221],"type":"Point"},"properties":{"Age":50,"AgeGroup":"3","City":"Brainerd","NumberofDeaths":1,"NumberofFemale":0,"NumberofMale":1,"State":"MN"},"type":"Feature"}]}