{"type":"FeatureCollection","features":[{"geometry":{"coordinates":[-85.25593921,34.018554],"type":"Point"},"properties":{"Age":59,"AgeGroup":"3","City":"Cedartown","NumberofDeaths":1,"NumberofFemale":0,"NumberofMale":1,"State":"GA"},"type":"Feature"}]}