{"type":"FeatureCollection","features":[{"geometry":{"coordinates":[-91.4917899,33.8870477],"type":"Point"},"properties":{"Age":31,"AgeGroup":"3","City":"Dumas","NumberofDeaths":1,"NumberofFemale":0,"NumberofMale":1,"State":"AR"},"type":"Feature"}]}