{"type":"FeatureCollection","features":[{"geometry":{"coordinates":[-120.5451223,46.9970635],"type":"Point"},"properties":{"Age":37,"AgeGroup":"3","City":"Ellensburg","NumberofDeaths":2,"NumberofFemale":0,"NumberofMale":2,"State":"WA"},"type":"Feature"}]}