{"type":"FeatureCollection","features":[{"geometry":{"coordinates":[-118.500478,34.1588478],"type":"Point"},"properties":{"Age":80,"AgeGroup":"3","City":"Encino","NumberofDeaths":1,"NumberofFemale":0,"NumberofMale":1,"State":"CA"},"type":"Feature"}]}