{"type":"FeatureCollection","features":[{"geometry":{"coordinates":[-80.085239,42.129461],"type":"Point"},"properties":{"Age":"","AgeGroup":"3","City":"Erie","NumberofDeaths":3,"NumberofFemale":0,"NumberofMale":3,"State":"PA"},"type":"Feature"}]}