{"type":"FeatureCollection","features":[{"geometry":{"coordinates":[-94.4846602,36.2675793],"type":"Point"},"properties":{"Age":"","AgeGroup":"3","City":"Gentry","NumberofDeaths":1,"NumberofFemale":0,"NumberofMale":1,"State":"AR"},"type":"Feature"}]}