{"type":"FeatureCollection","features":[{"geometry":{"coordinates":[-82.3915122,34.4465018],"type":"Point"},"properties":{"Age":38,"AgeGroup":"3","City":"HoneaPath","NumberofDeaths":1,"NumberofFemale":0,"NumberofMale":1,"State":"SC"},"type":"Feature"}]}