{"type":"FeatureCollection","features":[{"geometry":{"coordinates":[-78.4822938,35.7878975],"type":"Point"},"properties":{"Age":49,"AgeGroup":"3","City":"Knightdale","NumberofDeaths":2,"NumberofFemale":1,"NumberofMale":1,"State":"NC"},"type":"Feature"}]}