{"type":"FeatureCollection","features":[{"geometry":{"coordinates":[-82.2857055,39.2661831],"type":"Point"},"properties":{"Age":46,"AgeGroup":"3","City":"Knox","NumberofDeaths":2,"NumberofFemale":0,"NumberofMale":2,"State":"OH"},"type":"Feature"}]}