{"type":"FeatureCollection","features":[{"geometry":{"coordinates":[-105.0579688,40.1529745],"type":"Point"},"properties":{"Age":43,"AgeGroup":"3","City":"Longmont","NumberofDeaths":8,"NumberofFemale":4,"NumberofMale":4,"State":"CO"},"type":"Feature"}]}