{"type":"FeatureCollection","features":[{"geometry":{"coordinates":[-79.03056351,43.099685],"type":"Point"},"properties":{"Age":39,"AgeGroup":"3","City":"NiagaraFalls","NumberofDeaths":2,"NumberofFemale":1,"NumberofMale":1,"State":"NY"},"type":"Feature"}]}