{"type":"FeatureCollection","features":[{"geometry":{"coordinates":[-75.6496302,40.2453741],"type":"Point"},"properties":{"Age":22,"AgeGroup":"3","City":"Pottstown","NumberofDeaths":2,"NumberofFemale":0,"NumberofMale":2,"State":"PA"},"type":"Feature"}]}