{"type":"FeatureCollection","features":[{"geometry":{"coordinates":[-118.052829,34.1031775],"type":"Point"},"properties":{"Age":65,"AgeGroup":"3","City":"TempleCity","NumberofDeaths":1,"NumberofFemale":1,"NumberofMale":0,"State":"CA"},"type":"Feature"}]}